CHANGES.txt
COPYRIGHT.txt
LICENSE.txt
README.txt
bootstrap.py
buildout.cfg
setup.py
src/z3c/__init__.py
src/z3c.language.negotiator.egg-info/PKG-INFO
src/z3c.language.negotiator.egg-info/SOURCES.txt
src/z3c.language.negotiator.egg-info/dependency_links.txt
src/z3c.language.negotiator.egg-info/namespace_packages.txt
src/z3c.language.negotiator.egg-info/not-zip-safe
src/z3c.language.negotiator.egg-info/requires.txt
src/z3c.language.negotiator.egg-info/top_level.txt
src/z3c/language/__init__.py
src/z3c/language/negotiator/README.txt
src/z3c/language/negotiator/SETUP.cfg
src/z3c/language/negotiator/__init__.py
src/z3c/language/negotiator/app.py
src/z3c/language/negotiator/configure.zcml
src/z3c/language/negotiator/interfaces.py
src/z3c/language/negotiator/testing.py
src/z3c/language/negotiator/tests.py
src/z3c/language/negotiator/vocabulary.py
src/z3c/language/negotiator/z3c.language.negotiator-configure.zcml
src/z3c/language/negotiator/browser/__init__.py
src/z3c/language/negotiator/browser/configure.zcml
src/z3c/language/negotiator/browser/views.py
src/z3c/language/negotiator/browser/zmi.zcml
src/z3c/language/negotiator/generations/__init__.py
src/z3c/language/negotiator/generations/configure.zcml
src/z3c/language/negotiator/generations/evolve1.py